jupyterlab_niryo_one/__init__.py
jupyterlab_niryo_one/_version.py
jupyterlab_niryo_one-0.1.2.data/data/share/jupyter/labextensions/jupyterlab-niryo-one/package.json
jupyterlab_niryo_one-0.1.2.data/data/share/jupyter/labextensions/jupyterlab-niryo-one/static/156.84dd946e62898b89baf6.js
jupyterlab_niryo_one-0.1.2.data/data/share/jupyter/labextensions/jupyterlab-niryo-one/static/156.84dd946e62898b89baf6.js.map
jupyterlab_niryo_one-0.1.2.data/data/share/jupyter/labextensions/jupyterlab-niryo-one/static/194.a51c5d66e3db89a3fe77.js
jupyterlab_niryo_one-0.1.2.data/data/share/jupyter/labextensions/jupyterlab-niryo-one/static/194.a51c5d66e3db89a3fe77.js.map
jupyterlab_niryo_one-0.1.2.data/data/share/jupyter/labextensions/jupyterlab-niryo-one/static/222.660212533141898437bd.js
jupyterlab_niryo_one-0.1.2.data/data/share/jupyter/labextensions/jupyterlab-niryo-one/static/222.660212533141898437bd.js.map
jupyterlab_niryo_one-0.1.2.data/data/share/jupyter/labextensions/jupyterlab-niryo-one/static/250.1c4e3c2139fbccfc0e5f.js
jupyterlab_niryo_one-0.1.2.data/data/share/jupyter/labextensions/jupyterlab-niryo-one/static/250.1c4e3c2139fbccfc0e5f.js.map
jupyterlab_niryo_one-0.1.2.data/data/share/jupyter/labextensions/jupyterlab-niryo-one/static/287.76e1e4b3b756ba00a957.js
jupyterlab_niryo_one-0.1.2.data/data/share/jupyter/labextensions/jupyterlab-niryo-one/static/287.76e1e4b3b756ba00a957.js.map
jupyterlab_niryo_one-0.1.2.data/data/share/jupyter/labextensions/jupyterlab-niryo-one/static/310.7de38ce28ff7cfd5b623.js
jupyterlab_niryo_one-0.1.2.data/data/share/jupyter/labextensions/jupyterlab-niryo-one/static/310.7de38ce28ff7cfd5b623.js.map
jupyterlab_niryo_one-0.1.2.data/data/share/jupyter/labextensions/jupyterlab-niryo-one/static/318.bea6ca39dce3d86633de.js
jupyterlab_niryo_one-0.1.2.data/data/share/jupyter/labextensions/jupyterlab-niryo-one/static/318.bea6ca39dce3d86633de.js.map
jupyterlab_niryo_one-0.1.2.dist-info/METADATA
jupyterlab_niryo_one-0.1.2.dist-info/WHEEL
jupyterlab_niryo_one-0.1.2.dist-info/licenses/LICENSE
jupyterlab_niryo_one-0.1.2.dist-info/RECORD
