Metadata-Version: 2.3
Name: jupyterlab_niryo_one
Version: 0.1.2
Dynamic: Keywords
Summary: Blockly extension for JupyterLab to control the Niryo One robot.
Project-URL: Homepage, https://github.com/jupyter-robotics/jupyterlab-niryo-one
Project-URL: Bug Tracker, https://github.com/jupyter-robotics/jupyterlab-niryo-one/issues
Project-URL: Repository, https://github.com/jupyter-robotics/jupyterlab-niryo-one.git
Author: quantstack
License: BSD 3-Clause License
License-File: LICENSE
Classifier: Framework :: Jupyter
Classifier: Framework :: Jupyter :: JupyterLab
Classifier: Framework :: Jupyter :: JupyterLab :: 4
Classifier: Framework :: Jupyter :: JupyterLab :: Extensions
Classifier: Framework :: Jupyter :: JupyterLab :: Extensions :: Prebuilt
Classifier: License :: OSI Approved :: BSD License
Classifier: Programming Language :: Python
Classifier: Programming Language :: Python :: 3
Classifier: Programming Language :: Python :: 3.8
Classifier: Programming Language :: Python :: 3.9
Classifier: Programming Language :: Python :: 3.10
Classifier: Programming Language :: Python :: 3.11
Classifier: Programming Language :: Python :: 3.12
Requires-Python: >=3.8
Requires-Dist: jupyterlab-blockly<0.4,>=0.3.2
Requires-Dist: pyniryo<2,>=1.1.2
Provides-Extra: dev
Requires-Dist: click; extra == 'dev'
Requires-Dist: jupyter-releaser; extra == 'dev'
Requires-Dist: pre-commit; extra == 'dev'
Provides-Extra: env
Requires-Dist: pyniryo; extra == 'env'
